{
  "slug": "131732-kurtis-ellis",
  "name": "Kurtis Ellis",
  "nickname": "The Outcast",
  "aliases": [],
  "recordPro": {
    "wins": 3,
    "losses": 9,
    "draws": 0
  },
  "recordAmateur": null,
  "heightCm": 180,
  "reachCm": 188,
  "weightClass": "Featherweight",
  "stance": null,
  "dateOfBirth": "1993-05-01",
  "nationality": "United States",
  "url": "https://www.tapology.com/fightcenter/fighters/131732-kurtis-ellis",
  "recentFights": [
    {
      "date": "2026-05-16T00:00:00.000Z",
      "opponent": "Vincenzo Iannuzzo",
      "opponentSlug": "233402-vince-iannuzzo",
      "result": null,
      "method": "other",
      "event": "NEF 66: Salute",
      "eventSlug": "141323-nef-66-salute",
      "round": null,
      "timeInRound": null
    },
    {
      "date": "2026-03-29T00:00:00.000Z",
      "opponent": "Jeremy Strobel Jr.",
      "opponentSlug": "218643-jeremy-strobel-jr-the-sniper",
      "result": "loss",
      "method": "sub",
      "event": "Anthony Pettis FC 23",
      "eventSlug": "138664-anthony-pettis-fc-23-milwaukee-fight-night-10",
      "round": 1,
      "timeInRound": "1:25"
    },
    {
      "date": "2025-11-21T00:00:00.000Z",
      "opponent": "Josue Sotero",
      "opponentSlug": "351397-josue-sotero",
      "result": "loss",
      "method": "other",
      "event": "Art of Scrap 11",
      "eventSlug": "132985-art-of-scrap-11",
      "round": 1,
      "timeInRound": "0:46"
    },
    {
      "date": "2025-10-04T00:00:00.000Z",
      "opponent": "Jonah Andrews",
      "opponentSlug": "297427-jonah-andrews",
      "result": "loss",
      "method": "other",
      "event": "FAC 31: Fight 4 the Cure",
      "eventSlug": "131301-fac-31",
      "round": 1,
      "timeInRound": "2:01"
    },
    {
      "date": "2025-08-09T00:00:00.000Z",
      "opponent": "Eddie Perez",
      "opponentSlug": "61824-eddie-perez",
      "result": "loss",
      "method": "sub",
      "event": "Combat Night Kissimmee",
      "eventSlug": "131119-combat-night-kissimmee",
      "round": 1,
      "timeInRound": "2:52"
    },
    {
      "date": "2025-03-23T00:00:00.000Z",
      "opponent": "Brandon Evans",
      "opponentSlug": "294721-brandon-evans",
      "result": "loss",
      "method": "sub",
      "event": "Anthony Pettis FC 16",
      "eventSlug": "122516-anthony-pettis-fc-16-milwaukee-fight-night",
      "round": 3,
      "timeInRound": "0:35"
    },
    {
      "date": "2025-01-17T00:00:00.000Z",
      "opponent": "M,A,Yah II",
      "opponentSlug": "253452-mattia-ioi",
      "result": "loss",
      "method": "other",
      "event": "DCS 96: New Year's Knockouts 2025",
      "eventSlug": "122010-dcs-96-new-year-s-knockouts-2025",
      "round": 1,
      "timeInRound": "3:30"
    },
    {
      "date": "2024-06-22T00:00:00.000Z",
      "opponent": "Carlos Calderon",
      "opponentSlug": "149398-carlos-calderon",
      "result": "loss",
      "method": "sub",
      "event": "LFA 186: Bekoev vs. Foxworth",
      "eventSlug": "113089-lfa-186",
      "round": 1,
      "timeInRound": "2:31"
    },
    {
      "date": "2024-04-05T00:00:00.000Z",
      "opponent": "Canon Swanson",
      "opponentSlug": "329282-canon-swanson",
      "result": "win",
      "method": "other",
      "event": "LFA 181: Siqueira vs. Hernandez",
      "eventSlug": "110760-lfa-181",
      "round": 1,
      "timeInRound": "0:24"
    },
    {
      "date": "2023-06-24T00:00:00.000Z",
      "opponent": "Jordan Brown",
      "opponentSlug": "263904-jordan-brown",
      "result": "loss",
      "method": "sub",
      "event": "ECF 1: Showdown in the Falls",
      "eventSlug": "100198-ecf-1",
      "round": 1,
      "timeInRound": "4:07"
    },
    {
      "date": "2023-04-21T00:00:00.000Z",
      "opponent": "Griffin Parriott",
      "opponentSlug": "348161-griffin-parriott",
      "result": "loss",
      "method": "other",
      "event": "LFA 157: Croden vs. Cavalcanti",
      "eventSlug": "98777-lfa-157-croden-vs-cavalcanti",
      "round": 1,
      "timeInRound": "4:51"
    },
    {
      "date": "2023-03-25T00:00:00.000Z",
      "opponent": "Alex Coover",
      "opponentSlug": "186455-alex-coover",
      "result": "win",
      "method": "other",
      "event": "Caged Aggression 35",
      "eventSlug": "92882-caged-aggression-35-the-trilogy-night-3",
      "round": 1,
      "timeInRound": "3:44"
    },
    {
      "date": "2022-05-21T00:00:00.000Z",
      "opponent": "Paul Burgin",
      "opponentSlug": "56774-paul-burgin",
      "result": "win",
      "method": "other",
      "event": "North Iowa Fights",
      "eventSlug": "85336-north-iowa-fights",
      "round": 1,
      "timeInRound": "2:26"
    },
    {
      "date": "2021-06-04T00:00:00.000Z",
      "opponent": "Yunior Escobar",
      "opponentSlug": "204501-yunior-escobar",
      "result": "loss",
      "method": "sub",
      "event": "DCS 71: Summer Kick-Off Night 1",
      "eventSlug": "79400-dcs-71-summer-kick-off-night-1",
      "round": 1,
      "timeInRound": "2:17"
    },
    {
      "date": "2020-11-21T00:00:00.000Z",
      "opponent": "Levi Kilroy",
      "opponentSlug": "70783-levi-kilroy",
      "result": "win",
      "method": "other",
      "event": "Caged Aggression 29",
      "eventSlug": "72936-caged-aggression-29-determination-day-2",
      "round": 1,
      "timeInRound": "2:00"
    },
    {
      "date": "2020-10-30T00:00:00.000Z",
      "opponent": "Chandler Chapman",
      "opponentSlug": "237657-chandler-chapman",
      "result": "loss",
      "method": "tko",
      "event": "MCF 19: The Beatdown",
      "eventSlug": "72820-mcf-19-the-beatdown",
      "round": 2,
      "timeInRound": null
    },
    {
      "date": "2020-10-30T00:00:00.000Z",
      "opponent": "N. S.",
      "opponentSlug": "212761-n-s",
      "result": null,
      "method": "other",
      "event": "MCF 19: The Beatdown",
      "eventSlug": "72820-mcf-19-the-beatdown",
      "round": null,
      "timeInRound": null
    },
    {
      "date": "2019-08-23T00:00:00.000Z",
      "opponent": "Jesse Hannam",
      "opponentSlug": "154468-jesse-hannam",
      "result": "loss",
      "method": "sub",
      "event": "Caged Aggression 25",
      "eventSlug": "59216-caged-aggression-25-the-return-night-1",
      "round": 3,
      "timeInRound": "2:43"
    },
    {
      "date": "2019-06-01T00:00:00.000Z",
      "opponent": "Justin Gary",
      "opponentSlug": "49109-justin-gary",
      "result": "win",
      "method": "sub",
      "event": "MMA Evolved 2",
      "eventSlug": "60410-mma-evolved-2-salute-the-troops",
      "round": 1,
      "timeInRound": "1:22"
    },
    {
      "date": "2019-03-22T00:00:00.000Z",
      "opponent": "Motaz Askar",
      "opponentSlug": "150352-motaz-askar",
      "result": "loss",
      "method": "other",
      "event": "Caged Aggression 24",
      "eventSlug": "57335-caged-aggression-24-champions-night-1",
      "round": 1,
      "timeInRound": "2:30"
    },
    {
      "date": "2019-02-23T00:00:00.000Z",
      "opponent": "Ray Hedges",
      "opponentSlug": "92360-ray-hedges",
      "result": "win",
      "method": "sub",
      "event": "Elite Fight League 3",
      "eventSlug": "57280-elite-fight-league-3",
      "round": 1,
      "timeInRound": "2:14"
    },
    {
      "date": "2018-10-20T00:00:00.000Z",
      "opponent": "Ryan Houston",
      "opponentSlug": "73349-ryan-houston",
      "result": "loss",
      "method": "sub",
      "event": "Caged Aggression 23",
      "eventSlug": "55393-caged-aggression-23-the-rematches",
      "round": 1,
      "timeInRound": "2:50"
    },
    {
      "date": "2018-08-25T00:00:00.000Z",
      "opponent": "Brynn Heathcock",
      "opponentSlug": "105980-brynn-heathcock",
      "result": "win",
      "method": "dec-unanimous",
      "event": "Caged Aggression 22",
      "eventSlug": "53815-caged-aggression-catfish-bend-casino-day-2",
      "round": null,
      "timeInRound": null
    },
    {
      "date": "2018-06-08T00:00:00.000Z",
      "opponent": "Chris Sanchez",
      "opponentSlug": "120645-chris-sanchez",
      "result": "loss",
      "method": "sub",
      "event": "XFO: Noche De Lucha",
      "eventSlug": "52953-xfo-noche-de-lucha",
      "round": 1,
      "timeInRound": "1:34"
    },
    {
      "date": "2018-03-31T00:00:00.000Z",
      "opponent": "Mitchell Williams",
      "opponentSlug": "176447-mitchell-williams",
      "result": "loss",
      "method": "other",
      "event": "Birth of the Ogitchidaa",
      "eventSlug": "51362-birth-of-the-ogitchidaa",
      "round": 1,
      "timeInRound": "2:18"
    },
    {
      "date": "2018-01-13T00:00:00.000Z",
      "opponent": "Derrick Young",
      "opponentSlug": "166083-derrick-young",
      "result": "win",
      "method": "tko",
      "event": "Caged Aggression Challengers 6",
      "eventSlug": "49546-caged-aggression-challengers-6",
      "round": 1,
      "timeInRound": "2:20"
    },
    {
      "date": "2017-11-22T00:00:00.000Z",
      "opponent": "Josh Kristensen",
      "opponentSlug": "143979-josh-kristensen",
      "result": "loss",
      "method": "sub",
      "event": "Victory FC: Fight Night Waterloo 2",
      "eventSlug": "48666-victory-fc-fight-night-waterloo-2",
      "round": 2,
      "timeInRound": "0:44"
    },
    {
      "date": "2017-09-30T00:00:00.000Z",
      "opponent": "Josh McNabb",
      "opponentSlug": "132585-josh-mcnabb",
      "result": "win",
      "method": "sub",
      "event": "Extreme Challenge 236",
      "eventSlug": "47506-extreme-challenge-236",
      "round": 2,
      "timeInRound": "0:36"
    },
    {
      "date": "2017-08-05T00:00:00.000Z",
      "opponent": "Datrelle Kozeluh",
      "opponentSlug": "160772-datrelle-kozeluh",
      "result": "loss",
      "method": "sub",
      "event": "XFO 62: Outdoor War 13",
      "eventSlug": "45924-xfo-62-outdoor-war-13",
      "round": 1,
      "timeInRound": "1:10"
    },
    {
      "date": "2017-05-20T00:00:00.000Z",
      "opponent": "Alex Bartels",
      "opponentSlug": "157857-alex-bartels",
      "result": "win",
      "method": "sub",
      "event": "Pugna Entertainment",
      "eventSlug": "44790-pugna-entertainment",
      "round": 2,
      "timeInRound": "2:27"
    },
    {
      "date": "2017-01-28T00:00:00.000Z",
      "opponent": "Mason Teeters",
      "opponentSlug": "95352-mason-teeters",
      "result": "loss",
      "method": "other",
      "event": "Gateway Fighting Series 7",
      "eventSlug": "42938-gateway-fighting-series-7-retribution",
      "round": 3,
      "timeInRound": "2:52"
    },
    {
      "date": "2016-12-10T00:00:00.000Z",
      "opponent": "Dillon Reyes",
      "opponentSlug": "149343-dillon-reyes",
      "result": "loss",
      "method": "sub",
      "event": "Gateway Fighting Series 6",
      "eventSlug": "42935-gateway-fight-series-6-showdown",
      "round": 1,
      "timeInRound": "1:31"
    },
    {
      "date": "2016-11-25T00:00:00.000Z",
      "opponent": "Danny Bazarek",
      "opponentSlug": "134731-danny-bazarek",
      "result": "loss",
      "method": "sub",
      "event": "XFO: Rocktown Showdown 28",
      "eventSlug": "42456-xfo-rocktown-showdown-28",
      "round": 1,
      "timeInRound": "1:34"
    },
    {
      "date": "2016-10-22T00:00:00.000Z",
      "opponent": "Jesus Villegas",
      "opponentSlug": "119360-jesus-villegas",
      "result": "loss",
      "method": "sub",
      "event": "XFO: Fight Night",
      "eventSlug": "41555-xfo-fight-night",
      "round": 1,
      "timeInRound": "1:05"
    },
    {
      "date": "2016-10-01T00:00:00.000Z",
      "opponent": "Daniel Caldara",
      "opponentSlug": "97850-daniel-caldara",
      "result": "win",
      "method": "dec-unanimous",
      "event": "Back In The Barn 5",
      "eventSlug": "42815-back-in-the-barn-5",
      "round": null,
      "timeInRound": null
    },
    {
      "date": "2016-08-06T00:00:00.000Z",
      "opponent": "Kyial Sheriev",
      "opponentSlug": "121196-kyial-sheriev",
      "result": "win",
      "method": "dec-unanimous",
      "event": "XFO 59: Outdoor War 12",
      "eventSlug": "40369-xfo-59",
      "round": null,
      "timeInRound": null
    },
    {
      "date": "2016-06-25T00:00:00.000Z",
      "opponent": "David Stieneke",
      "opponentSlug": "36074-david-stineke",
      "result": "loss",
      "method": "sub",
      "event": "KOTC: Summer Smash",
      "eventSlug": "39843-kotc-summer-smash",
      "round": 3,
      "timeInRound": "0:58"
    },
    {
      "date": "2016-06-11T00:00:00.000Z",
      "opponent": "Tou Vang",
      "opponentSlug": "122161-tou-vang",
      "result": "loss",
      "method": "sub",
      "event": "Pure FC 4",
      "eventSlug": "39471-pure-fc-4",
      "round": 2,
      "timeInRound": "2:43"
    },
    {
      "date": "2016-06-04T00:00:00.000Z",
      "opponent": "Aaron Mitchell",
      "opponentSlug": "67270-aaron-mitchell",
      "result": "loss",
      "method": "sub",
      "event": "Laramar Fight Night 11",
      "eventSlug": "40106-laramar-fight-night-11",
      "round": 1,
      "timeInRound": "1:19"
    },
    {
      "date": "2016-05-20T00:00:00.000Z",
      "opponent": "Austin Roybal",
      "opponentSlug": "109280-austin-roybal",
      "result": "win",
      "method": "sub",
      "event": "Conquest Promotions",
      "eventSlug": "39573-conquest-promotions-clash-on-the-high-plains",
      "round": 1,
      "timeInRound": "1:37"
    }
  ],
  "lastVerified": "2026-04-18T07:40:59.253Z"
}
