{
  "slug": "93065-morgan-charriere",
  "name": "Morgan Charrière",
  "nickname": "The Last Pirate",
  "aliases": [],
  "recordPro": {
    "wins": 21,
    "losses": 12,
    "draws": 1
  },
  "recordAmateur": null,
  "heightCm": 173,
  "reachCm": 175,
  "weightClass": "Featherweight",
  "stance": null,
  "dateOfBirth": "1995-10-26",
  "nationality": "Poissy, France",
  "url": "https://www.tapology.com/fightcenter/fighters/93065-morgan-charriere",
  "recentFights": [
    {
      "date": "2025-12-13T00:00:00.000Z",
      "opponent": "Melquizael Costa",
      "opponentSlug": "101043-melquizael-costa-melkcalty",
      "result": "loss",
      "method": "other",
      "event": "UFC Fight Night",
      "eventSlug": "132921-ufc-fight-night",
      "round": 1,
      "timeInRound": "1:14"
    },
    {
      "date": "2025-07-12T00:00:00.000Z",
      "opponent": "Nate Landwehr",
      "opponentSlug": "26263-nate-landwehr",
      "result": "win",
      "method": "other",
      "event": "UFC Fight Night",
      "eventSlug": "126523-ufc-fight-night",
      "round": 3,
      "timeInRound": "0:27"
    },
    {
      "date": "2025-03-22T00:00:00.000Z",
      "opponent": "Nathaniel Wood",
      "opponentSlug": "27454-nathaniel-wood",
      "result": "loss",
      "method": "dec-unanimous",
      "event": "UFC Fight Night",
      "eventSlug": "120214-ufc-fight-night",
      "round": null,
      "timeInRound": null
    },
    {
      "date": "2024-09-28T00:00:00.000Z",
      "opponent": "Gabriel Miranda",
      "opponentSlug": "36548-gabriel-miranda-fly",
      "result": "win",
      "method": "other",
      "event": "UFC Fight Night",
      "eventSlug": "111674-ufc-fight-night",
      "round": 2,
      "timeInRound": "0:27"
    },
    {
      "date": "2024-04-06T00:00:00.000Z",
      "opponent": "Chepe Mariscal",
      "opponentSlug": "44895-jose-mariscal",
      "result": "loss",
      "method": "dec-split",
      "event": "UFC Fight Night",
      "eventSlug": "108721-ufc-fight-night",
      "round": null,
      "timeInRound": null
    },
    {
      "date": "2023-09-02T00:00:00.000Z",
      "opponent": "Manolo Zecchini",
      "opponentSlug": "122701-manolo-zecchini",
      "result": "win",
      "method": "other",
      "event": "UFC Fight Night",
      "eventSlug": "102007-ufc-fight-night",
      "round": 1,
      "timeInRound": "3:51"
    },
    {
      "date": "2023-07-21T00:00:00.000Z",
      "opponent": "Diego Silva",
      "opponentSlug": "69638-diego-silva",
      "result": "win",
      "method": "other",
      "event": "Cage Warriors 157",
      "eventSlug": "99929-cage-warriors-london",
      "round": 3,
      "timeInRound": "4:13"
    },
    {
      "date": "2023-04-29T00:00:00.000Z",
      "opponent": "Pedro Souza",
      "opponentSlug": "52690-pedro-souza",
      "result": "win",
      "method": "other",
      "event": "Cage Warriors 153",
      "eventSlug": "97499-cage-warriors-153-dublin",
      "round": 1,
      "timeInRound": "5:00"
    },
    {
      "date": "2022-11-20T00:00:00.000Z",
      "opponent": "Daniel Bažant",
      "opponentSlug": "223718-daniel-bazant",
      "result": "win",
      "method": "dec-split",
      "event": "Cage Warriors 147",
      "eventSlug": "93986-cage-warriors-147-unplugged",
      "round": null,
      "timeInRound": null
    },
    {
      "date": "2021-10-01T00:00:00.000Z",
      "opponent": "Paul Hughes",
      "opponentSlug": "35866-paul-hughes",
      "result": "loss",
      "method": "dec-majority",
      "event": "Cage Warriors 128",
      "eventSlug": "80684-cage-warriors-128",
      "round": null,
      "timeInRound": null
    },
    {
      "date": "2021-03-20T00:00:00.000Z",
      "opponent": "Jordan Vucenic",
      "opponentSlug": "106035-jordan-vucenic",
      "result": "loss",
      "method": "dec-split",
      "event": "Cage Warriors 122",
      "eventSlug": "74960-cage-warriors-122",
      "round": null,
      "timeInRound": null
    },
    {
      "date": "2020-12-12T00:00:00.000Z",
      "opponent": "Perry Andre Goodwin",
      "opponentSlug": "31247-perry-andre-goodwin",
      "result": "win",
      "method": "other",
      "event": "Cage Warriors 119",
      "eventSlug": "73177-cage-warriors-119",
      "round": 3,
      "timeInRound": "1:45"
    },
    {
      "date": "2019-10-26T00:00:00.000Z",
      "opponent": "Dean Trueman",
      "opponentSlug": "27061-dean-trueman",
      "result": "win",
      "method": "other",
      "event": "Cage Warriors 109",
      "eventSlug": "60771-cage-warriors-109",
      "round": 3,
      "timeInRound": "1:08"
    },
    {
      "date": "2019-06-29T00:00:00.000Z",
      "opponent": "Lewis Monarch",
      "opponentSlug": "59505-lewis-monarch",
      "result": "win",
      "method": "dec-split",
      "event": "Cage Warriors 106",
      "eventSlug": "59937-cage-warriors-106-night-of-champions",
      "round": null,
      "timeInRound": null
    },
    {
      "date": "2019-03-09T00:00:00.000Z",
      "opponent": "Soren Bak",
      "opponentSlug": "32825-soren-bak",
      "result": "loss",
      "method": "dec-majority",
      "event": "Cage Warriors 103",
      "eventSlug": "55681-cage-warriors-103",
      "round": null,
      "timeInRound": null
    },
    {
      "date": "2018-12-15T00:00:00.000Z",
      "opponent": "Marko Kovacevic",
      "opponentSlug": "28353-marko-kovacevic",
      "result": "draw",
      "method": "dec-split",
      "event": "WWFC 13",
      "eventSlug": "56082-wwfc-13",
      "round": null,
      "timeInRound": null
    },
    {
      "date": "2018-10-13T00:00:00.000Z",
      "opponent": "Julien Graco",
      "opponentSlug": "102926-julien-graco",
      "result": "win",
      "method": "other",
      "event": "European Beatdown 4",
      "eventSlug": "54720-european-beatdown-4",
      "round": 1,
      "timeInRound": "0:37"
    },
    {
      "date": "2018-03-24T00:00:00.000Z",
      "opponent": "Ruslan Khazmurzaev",
      "opponentSlug": "156454-ruslan-khazmurzaev",
      "result": "loss",
      "method": "dec-majority",
      "event": "WWFC 10",
      "eventSlug": "51692-wwfc-10",
      "round": null,
      "timeInRound": null
    },
    {
      "date": "2017-12-14T00:00:00.000Z",
      "opponent": "Alexey Oleinik",
      "opponentSlug": "64765-alexey-oleinik",
      "result": "win",
      "method": "other",
      "event": "WWFC 9",
      "eventSlug": "48623-wwfc-9",
      "round": 2,
      "timeInRound": "4:50"
    },
    {
      "date": "2017-10-28T00:00:00.000Z",
      "opponent": "Geysim Derouiche",
      "opponentSlug": "150178-zidane-geisym",
      "result": "win",
      "method": "tko",
      "event": "Octagon Fighting Club 17",
      "eventSlug": "48713-octagon-fighting-club-17",
      "round": 3,
      "timeInRound": "2:00"
    },
    {
      "date": "2017-03-17T00:00:00.000Z",
      "opponent": "Salahdine Parnasse",
      "opponentSlug": "118604-salahdine-parnasse",
      "result": "loss",
      "method": "dec-unanimous",
      "event": "100% Fight 29",
      "eventSlug": "44541-100-fight-29",
      "round": null,
      "timeInRound": null
    },
    {
      "date": "2017-03-17T00:00:00.000Z",
      "opponent": "Ciro Ruotolo",
      "opponentSlug": "26271-ciro-ruotolo",
      "result": "win",
      "method": "tko",
      "event": "100% Fight 29",
      "eventSlug": "44541-100-fight-29",
      "round": 1,
      "timeInRound": "4:30"
    },
    {
      "date": "2016-11-26T00:00:00.000Z",
      "opponent": "William Gomis",
      "opponentSlug": "125696-william-gomis",
      "result": "win",
      "method": "sub",
      "event": "100% Fight: Contenders 33",
      "eventSlug": "42737-100-fight-contenders-33",
      "round": 2,
      "timeInRound": "1:06"
    },
    {
      "date": "2016-11-12T00:00:00.000Z",
      "opponent": "Alex Kherfallah",
      "opponentSlug": "116921-alex-kherfallah",
      "result": "win",
      "method": "sub",
      "event": "Octagon Fighting Club 16",
      "eventSlug": "42771-octagon-fighting-club-16",
      "round": 1,
      "timeInRound": "2:10"
    },
    {
      "date": "2016-05-14T00:00:00.000Z",
      "opponent": "Pierre Sauvage",
      "opponentSlug": "90464-pierre-sauvage",
      "result": "loss",
      "method": "dec-unanimous",
      "event": "100% Fight 28",
      "eventSlug": "39625-100-fight-28-fight-for-the-belts",
      "round": null,
      "timeInRound": null
    },
    {
      "date": "2016-04-17T00:00:00.000Z",
      "opponent": "Ivan Dutchak",
      "opponentSlug": "169670-ivan-dutchak",
      "result": "win",
      "method": null,
      "event": null,
      "eventSlug": null,
      "round": null,
      "timeInRound": null
    },
    {
      "date": "2016-04-17T00:00:00.000Z",
      "opponent": "Banjougou Sidibe",
      "opponentSlug": "129116-banjougou-sidibe",
      "result": "win",
      "method": null,
      "event": null,
      "eventSlug": null,
      "round": null,
      "timeInRound": null
    },
    {
      "date": "2016-03-27T00:00:00.000Z",
      "opponent": "Jonathan Hilderald",
      "opponentSlug": "142710-jonathan-hilderald",
      "result": "win",
      "method": null,
      "event": null,
      "eventSlug": null,
      "round": null,
      "timeInRound": null
    },
    {
      "date": "2016-02-04T00:00:00.000Z",
      "opponent": "Drice Bouromel",
      "opponentSlug": "82210-drice-bouromel",
      "result": "win",
      "method": "dec-unanimous",
      "event": "100% Fight 27",
      "eventSlug": "37740-100-fight-27",
      "round": null,
      "timeInRound": null
    },
    {
      "date": "2015-12-20T00:00:00.000Z",
      "opponent": "Martin Avetisyan",
      "opponentSlug": "110206-martin-avetisyan",
      "result": "loss",
      "method": "dec-split",
      "event": "F&G Brest",
      "eventSlug": "60450-fgb",
      "round": null,
      "timeInRound": null
    },
    {
      "date": "2015-07-04T00:00:00.000Z",
      "opponent": "Christian Nkongo",
      "opponentSlug": "116881-christian-nkongo",
      "result": "loss",
      "method": null,
      "event": null,
      "eventSlug": null,
      "round": null,
      "timeInRound": null
    },
    {
      "date": "2015-06-20T00:00:00.000Z",
      "opponent": "Jean Loua",
      "opponentSlug": "79948-jean-loua",
      "result": "loss",
      "method": null,
      "event": null,
      "eventSlug": null,
      "round": null,
      "timeInRound": null
    },
    {
      "date": "2015-04-04T00:00:00.000Z",
      "opponent": "Ayadi Majdeddine",
      "opponentSlug": "79936-ayadi-majdeddine",
      "result": "loss",
      "method": null,
      "event": null,
      "eventSlug": null,
      "round": null,
      "timeInRound": null
    },
    {
      "date": "2014-12-13T00:00:00.000Z",
      "opponent": "Karim Kondua",
      "opponentSlug": "12718-karim-kondua",
      "result": "win",
      "method": null,
      "event": null,
      "eventSlug": null,
      "round": null,
      "timeInRound": null
    }
  ],
  "lastVerified": "2026-04-25T23:55:26.758Z"
}
